minimax_tts_openai/__main__.py
minimax_tts_openai/app.py
minimax_tts_openai/config.py
minimax_tts_openai/config.yaml.example
minimax_tts_openai-0.0.4.dist-info/METADATA
minimax_tts_openai-0.0.4.dist-info/WHEEL
minimax_tts_openai-0.0.4.dist-info/entry_points.txt
minimax_tts_openai-0.0.4.dist-info/top_level.txt
minimax_tts_openai-0.0.4.dist-info/RECORD
